avatar/__init__.py
avatar/aio.py
avatar/pandora_client.py
avatar/pandora_server.py
avatar/pandora_snippet.py
avatar/py.typed
avatar/runner.py
avatar/cases/__init__.py
avatar/cases/config.yml
avatar/cases/host_test.py
avatar/cases/le_host_test.py
avatar/cases/le_security_test.py
avatar/cases/security_test.py
avatar/controllers/__init__.py
avatar/controllers/bumble_device.py
avatar/controllers/pandora_device.py
avatar/controllers/usb_bumble_device.py
avatar/metrics/README.md
avatar/metrics/__init__.py
avatar/metrics/interceptors.py
avatar/metrics/trace.proto
avatar/metrics/trace.py
avatar/metrics/trace_pb2.py
avatar/metrics/trace_pb2.pyi
pandora_avatar-0.0.11.dist-info/entry_points.txt
pandora_avatar-0.0.11.dist-info/WHEEL
pandora_avatar-0.0.11.dist-info/METADATA
pandora_avatar-0.0.11.dist-info/RECORD
