Metadata-Version: 2.1
Name: pandora-avatar
Version: 0.0.11
Summary: Avatar is a scalable multi-platform Bluetooth testing tool capable of running
Author-email: Pandora <pandora-core@google.com>
Requires-Python: >=3.8
Classifier: Programming Language :: Python :: 3.10
Classifier: License :: OSI Approved :: Apache Software License
Requires-Dist: bt-test-interfaces>=0.0.6
Requires-Dist: bumble>=0.0.199
Requires-Dist: protobuf==4.24.2
Requires-Dist: grpcio>=1.62.1
Requires-Dist: mobly==1.12.2
Requires-Dist: portpicker>=1.5.2
Requires-Dist: rootcanal>=1.10.0 ; extra == "dev"
Requires-Dist: grpcio-tools>=1.62.1 ; extra == "dev"
Requires-Dist: pyright==1.1.298 ; extra == "dev"
Requires-Dist: mypy==1.5.1 ; extra == "dev"
Requires-Dist: black==24.10.0 ; extra == "dev"
Requires-Dist: isort==5.12.0 ; extra == "dev"
Requires-Dist: types-psutil==5.9.5.16 ; extra == "dev"
Requires-Dist: types-setuptools==68.1.0.1 ; extra == "dev"
Requires-Dist: types-protobuf==4.24.0.1 ; extra == "dev"
Project-URL: Source, https://github.com/google/avatar
Provides-Extra: dev
